[
  {
    "label": "лейтенант Синєгуб С.В.",
    "value": "командира 1 навчальної роти викладача лейтенанта Синєгуба С.В."
  },
  {
    "label": "сержант Троян І.П.",
    "value": "інструктора навчального взводу 1 навчальної роти сержанта Трояна І.П."
  },
  {
    "label": "молодший лейтенант Нижник О.А.",
    "value": "командира 4 навчального взводу 1 навчальної роти молодшого лейтенанта Нижника О.А."
  },
  {
    "label": "сержант Михайлюк С.В.",
    "value": "сержанта-інструктора циклової комісії загальновійськових дисциплін сержанта Михайлюк С.В."
  },
  {
    "label": "молодший сержант Ращупкін П.П.",
    "value": "інструктора навчального взводу 1 навчальної роти молодшого сержанта Ращупкіна П.П."
  },
  {
    "label": "сержант Баяк Т.Б.",
    "value": "санітарного інструктора 4 навчальної роти сержанта Баяк Т.Б."
  }
]